{
    "os": "macOS-15.1-arm64-arm-64bit",
    "python": "3.12.2",
    "heartbeatAt": "2025-03-05T16:02:21.857794",
    "startedAt": "2025-03-05T16:02:20.557366",
    "docker": null,
    "cuda": null,
    "args": [],
    "state": "running",
    "program": "/Users/nilaygaitonde/Documents/Projects/cv_project/face-detection.py",
    "codePathLocal": "face-detection.py",
    "codePath": "face-detection.py",
    "host": "Nilays-MacBook-Air.local",
    "username": "nilaygaitonde",
    "executable": "/Users/nilaygaitonde/anaconda3/envs/deeplearning/bin/python",
    "cpu_count": 8,
    "cpu_count_logical": 8,
    "disk": {
        "/": {
            "total": 228.27386474609375,
            "used": 224.1199607849121
        }
    },
    "gpuapple": {
        "type": "arm",
        "vendor": "Apple"
    },
    "memory": {
        "total": 8.0
    }
}
